<categories>
    <category idnumber='5' name='ESO'>
        <category idnumber='51' name='Primero'></category>
        <category idnumber='52' name='Segundo'></category>
        <category idnumber='53' name='Tercero'></category>
        <category idnumber='54' name='Cuarto'></category>
        <category idnumber='55 'name='PMAR'>
            <category idnumber='PMAR1' name='Primero'></category>
            <category idnumber='PMAR2' name='Segundo'></category>
        </category>
        <category idnumber='6' name='Bachillerato'>
            <category idnumber='61' name='Primero'></category>
            <category idnumber='62' name='Segundo'></category>
            <category idnumber='60' name='Proyectos de trabajo'></category>
        </category>
        <category idnumber='4' name='Sala de profesorado'></category>
    </categories>

    <categories>
        <category name='Miscelánea'></category>
        <category idnumber='2' name='ESO'>
            <category idnumber='21' name='Primero'></category>
            <category idnumber='22' name='Segundo'></category>
            <category idnumber='23' name='Tercero'></category>
            <category idnumber='24' name='Cuarto'></category>
            <category name='PMAR'>
                <category idnumber='PMAR1' name='Primero'></category>
                <category idnumber='PMAR2' name='Segundo'></category>
            </category>
        </category>
        <category idnumber='3' name='Bachillerato'>
            <category idnumber='31' name='Primero'></category>
            <category idnumber='32' name='Segundo'></category>
            <category idnumber='30' name='Proyectos de trabajo'></category>
        </category>
        <category name='Sala de profesorado'></category>
    </categories>